versupy/__init__.py
versupy/competitor.py
versupy/double_elim.py
versupy/match.py
versupy/round_robin.py
versupy/single_elim.py
versupy/swiss.py
versupy/tournament.py
versupy-0.1.0.dist-info/licenses/LICENSE
versupy-0.1.0.dist-info/METADATA
versupy-0.1.0.dist-info/WHEEL
versupy-0.1.0.dist-info/top_level.txt
versupy-0.1.0.dist-info/RECORD
