Metadata-Version: 2.4
Name: versupy
Version: 0.1.0
Summary: A Python library for creating and managing tournament brackets
Author: Elijah Wilts
License: MIT
Project-URL: Homepage, https://github.com/yourusername/versupy
Project-URL: Bug Reports, https://github.com/yourusername/versupy/issues
Project-URL: Source, https://github.com/yourusername/versupy
Keywords: tournament,bracket,competition,sports,gaming
Classifier: Development Status :: 3 - Alpha
Classifier: Intended Audience :: Developers
Classifier: License :: OSI Approved :: MIT License
Classifier: Programming Language :: Python :: 3
Classifier: Programming Language :: Python :: 3.8
Classifier: Programming Language :: Python :: 3.9
Classifier: Programming Language :: Python :: 3.10
Classifier: Programming Language :: Python :: 3.11
Classifier: Programming Language :: Python :: 3.12
Classifier: Topic :: Games/Entertainment
Classifier: Topic :: Software Development :: Libraries :: Python Modules
Requires-Python: >=3.8
License-File: LICENSE
Provides-Extra: dev
Requires-Dist: pytest>=7.0; extra == "dev"
Requires-Dist: black; extra == "dev"
Requires-Dist: flake8; extra == "dev"
Requires-Dist: mypy; extra == "dev"
Dynamic: license-file
